first/__init__.py
first/affine_Crypto.py
first/base64_ascii.py
first/blindSQLIN.py
first/crack_Matryoshka_zip.py
first/eight_thex_Hexstring.py
first/eighthex_string.py
first/grep_Php_code.py
first/number_To_ascii.py
first/offset.py
first/p_S.py
first/png_Realsize.py
second/__init__.py
second/message.py
lcxscenario-0.0.4.dist-info/LICENSE
lcxscenario-0.0.4.dist-info/METADATA
lcxscenario-0.0.4.dist-info/WHEEL
lcxscenario-0.0.4.dist-info/top_level.txt
lcxscenario-0.0.4.dist-info/RECORD
