Metadata-Version: 2.1
Name: lcxscenario
Version: 0.0.4
Summary: lcx
Home-page: UNKNOWN
Author: lcx
Author-email: UNKNOWN
License: UNKNOWN
Platform: UNKNOWN
